bsdm/__init__.py
bsdm/classes/__init__.py
bsdm/classes/Drawing.py
bsdm/classes/ETAttr.py
bsdm/classes/ETAttrMarker.py
bsdm/classes/ETBlock.py
bsdm/classes/ETName.py
bsdm/classes/Layout.py
bsdm/classes/RelAnchor.py
bsdm/classes/Relation.py
bsdm/classes/RelName.py
bsdm/classes/Text.py
bsdm/main.py
bsdm/utils/__init__.py
bsdm/utils/config.py
bsdm/utils/logger.py
bsdm/utils/StyleSheet.py
bsdm-0.9.0.dist-info/LICENSE
bsdm-0.9.0.dist-info/METADATA
bsdm-0.9.0.dist-info/WHEEL
bsdm-0.9.0.dist-info/RECORD
